{
  "id": 140,
  "date": "21.01.1896",
  "newborn": {
    "familia": "Тайченачева",
    "name": "Ксения",
    "patronym": "Герасимовна"
  },
  "father": {
    "familia": "Тайченачев",
    "name": "Герасим",
    "patronym": "Стефанович"
  },
  "mother": {
    "familia": "Тайченачева",
    "name": "Феодосия",
    "patronym": "Евфимиевна"
  },
  "locality": "Подаик",
  "susceptors": {
    "1st": {
      "familia": "Тайченачев",
      "name": "Иван",
      "patronym": "Васильевич"
    },
    "2nd": {
      "familia": "Шубина",
      "name": "Екатерина",
      "patronym": "Сергеевна"
    }
  },
  "notes": "-"
}